{
    "random_pfd": [
        0.091,
        0.1937,
        0.2841,
        0.3899,
        0.4871,
        0.5892,
        0.6925,
        0.7921,
        0.8998,
        1.0
    ],
    "deepGini_pfd": [
        0.2362,
        0.4071,
        0.5517,
        0.695,
        0.7964,
        0.8831,
        0.9348,
        0.9643,
        0.9834,
        1.0
    ],
    "vanillasoftmax_pfd": [
        0.2589,
        0.4705,
        0.6371,
        0.7503,
        0.8438,
        0.8979,
        0.9385,
        0.9705,
        0.9852,
        1.0
    ],
    "pcs_pfd": [
        0.27,
        0.4957,
        0.6494,
        0.7737,
        0.8407,
        0.9077,
        0.9477,
        0.9772,
        0.9889,
        1.0
    ],
    "entropy_pfd": [
        0.2325,
        0.3961,
        0.5332,
        0.6673,
        0.7638,
        0.861,
        0.9182,
        0.9582,
        0.9803,
        1.0
    ],
    "our_pfd": [
        0.4846,
        0.7405,
        0.8598,
        0.9108,
        0.949,
        0.9668,
        0.9803,
        0.9883,
        0.9945,
        1.0
    ]
}